pyschism/__init__.py
pyschism/__main__.py
pyschism/dates.py
pyschism/driver.py
pyschism/enums.py
pyschism/figures.py
pyschism/hotstart.py
pyschism/makefile.py
pyschism/stations.py
pyschism/cmd/__init__.py
pyschism/cmd/_nudge.py
pyschism/cmd/base.py
pyschism/cmd/basedaemon.py
pyschism/cmd/bctides.py
pyschism/cmd/common.py
pyschism/cmd/fluxflag.py
pyschism/cmd/forecast.py
pyschism/cmd/grd2sms.py
pyschism/cmd/hgrid.py
pyschism/cmd/outputs.py
pyschism/cmd/sflux.py
pyschism/cmd/sms2grd.py
pyschism/cmd/stations.py
pyschism/cmd/tvdflag.py
pyschism/cmd/vgrid.py
pyschism/cmd/_forecast/__init__.py
pyschism/cmd/_forecast/_init.py
pyschism/cmd/_forecast/_update.py
pyschism/cmd/bootstrap/__init__.py
pyschism/cmd/bootstrap/bootstrap.py
pyschism/cmd/fgrid/__init__.py
pyschism/cmd/fgrid/entry.py
pyschism/cmd/fgrid/manning.py
pyschism/forcing/__init__.py
pyschism/forcing/base.py
pyschism/forcing/bctides/__init__.py
pyschism/forcing/bctides/base.py
pyschism/forcing/bctides/bctides.py
pyschism/forcing/bctides/fes2014.py
pyschism/forcing/bctides/hamtide.py
pyschism/forcing/bctides/tides.py
pyschism/forcing/bctides/tpxo.py
pyschism/forcing/hycom/__init__.py
pyschism/forcing/hycom/base.py
pyschism/forcing/hycom/gofs.py
pyschism/forcing/hycom/hycom2schism.py
pyschism/forcing/hycom/rtofs2schism.py
pyschism/forcing/nws/__init__.py
pyschism/forcing/nws/base.py
pyschism/forcing/nws/best_track.py
pyschism/forcing/nws/tcprof.py
pyschism/forcing/nws/nws2/__init__.py
pyschism/forcing/nws/nws2/era5.py
pyschism/forcing/nws/nws2/gfs.py
pyschism/forcing/nws/nws2/gfs2.py
pyschism/forcing/nws/nws2/hrrr.py
pyschism/forcing/nws/nws2/hrrr2.py
pyschism/forcing/nws/nws2/hrrr3.py
pyschism/forcing/nws/nws2/nws2.py
pyschism/forcing/nws/nws2/sflux.py
pyschism/forcing/nws/nws2/sflux_inputs.txt
pyschism/forcing/source_sink/__init__.py
pyschism/forcing/source_sink/base.py
pyschism/forcing/source_sink/nwm.py
pyschism/forcing/source_sink/sflux2source/SourceSinkIn.py
pyschism-0.1.15.dist-info/LICENSE.txt
pyschism-0.1.15.dist-info/METADATA
pyschism-0.1.15.dist-info/WHEEL
pyschism-0.1.15.dist-info/entry_points.txt
pyschism-0.1.15.dist-info/top_level.txt
pyschism-0.1.15.dist-info/RECORD
