Metadata-Version: 2.1
Name: pyschism
Version: 0.1.15
Summary: Python package for working with SCHISM input and output files.
Home-page: https://github.com/schism-dev/pyschism.git
Author: "SCHISM development group"
Author-email: jreniel@gmail.com, lcui@vims.edu
License: "Apache 2.0"
Requires-Python: >3.6
License-File: LICENSE.txt
Requires-Dist: boto3
Requires-Dist: cdsapi
Requires-Dist: cf-python
Requires-Dist: cfgrib
Requires-Dist: f90nml
Requires-Dist: fsspec
Requires-Dist: geopandas
Requires-Dist: metpy
Requires-Dist: netCDF4
Requires-Dist: netcdf-flattener >=1.2.0
Requires-Dist: numba
Requires-Dist: ordered-set
Requires-Dist: psutil
Requires-Dist: pygeos
Requires-Dist: pyugrid
Requires-Dist: rtree
Requires-Dist: scipy
Requires-Dist: seawater
Requires-Dist: sqlalchemy
Requires-Dist: stormevents
Requires-Dist: tqdm
Requires-Dist: tqdm-logging-wrapper
Requires-Dist: utm
Requires-Dist: wget
Requires-Dist: xarray
Requires-Dist: xmltodict
Requires-Dist: zarr
Requires-Dist: appdirs
Requires-Dist: pylib-essentials
Provides-Extra: dev
Requires-Dist: coverage ; extra == 'dev'
Requires-Dist: flake8 ; extra == 'dev'
Requires-Dist: nose ; extra == 'dev'
